pyspark_storydoc/__init__.py
pyspark_storydoc/config.py
pyspark_storydoc/version.py
pyspark_storydoc/analysis/__init__.py
pyspark_storydoc/analysis/comprehensive_tracker.py
pyspark_storydoc/analysis/correlation_analyzer.py
pyspark_storydoc/analysis/describe_profiler.py
pyspark_storydoc/analysis/distribution_analyzer.py
pyspark_storydoc/analysis/distribution_decorator.py
pyspark_storydoc/analysis/expression_extractor.py
pyspark_storydoc/analysis/expression_lineage_decorator.py
pyspark_storydoc/analysis/impact_analyzer.py
pyspark_storydoc/core/__init__.py
pyspark_storydoc/core/config.py
pyspark_storydoc/core/context_managers.py
pyspark_storydoc/core/decorators.py
pyspark_storydoc/core/enhanced_lineage_graph.py
pyspark_storydoc/core/execution_context.py
pyspark_storydoc/core/fork_detector.py
pyspark_storydoc/core/graph_builder.py
pyspark_storydoc/core/hierarchy_context.py
pyspark_storydoc/core/lineage_dataframe.py
pyspark_storydoc/core/lineage_grouped_data.py
pyspark_storydoc/core/lineage_id.py
pyspark_storydoc/core/lineage_tracker.py
pyspark_storydoc/data_scientist/__init__.py
pyspark_storydoc/data_scientist/feature_catalog.py
pyspark_storydoc/data_scientist/reproducibility_report.py
pyspark_storydoc/data_scientist/statistical_profiler.py
pyspark_storydoc/data_scientist/statistical_report_generator.py
pyspark_storydoc/governance/__init__.py
pyspark_storydoc/governance/ai_inference.py
pyspark_storydoc/governance/audit_report.py
pyspark_storydoc/governance/bias_detection.py
pyspark_storydoc/governance/builders.py
pyspark_storydoc/governance/catalog.py
pyspark_storydoc/governance/comprehensive_catalog.py
pyspark_storydoc/governance/customer_impact.py
pyspark_storydoc/governance/enhanced_metadata.py
pyspark_storydoc/governance/governance_context.py
pyspark_storydoc/governance/integrated_report.py
pyspark_storydoc/governance/metadata.py
pyspark_storydoc/governance/reporting.py
pyspark_storydoc/governance/risk_assessment.py
pyspark_storydoc/governance/validation.py
pyspark_storydoc-0.3.0.dist-info/METADATA
pyspark_storydoc-0.3.0.dist-info/WHEEL
pyspark_storydoc-0.3.0.dist-info/entry_points.txt
pyspark_storydoc-0.3.0.dist-info/top_level.txt
pyspark_storydoc-0.3.0.dist-info/RECORD
