Metadata-Version: 2.4
Name: pyspark-storydoc
Version: 0.3.0
Summary: Business-friendly data lineage documentation for PySpark
Home-page: https://github.com/pyspark-storydoc/pyspark-storydoc
Author: PySpark StoryDoc Team
Author-email: PySpark StoryDoc Team <team@pysparkstorydoc.com>
Maintainer-email: PySpark StoryDoc Team <team@pysparkstorydoc.com>
License-Expression: CC-BY-NC-SA-4.0
Project-URL: Homepage, https://github.com/pyspark-storydoc/pyspark-storydoc
Project-URL: Documentation, https://pyspark-storydoc.readthedocs.io/
Project-URL: Repository, https://github.com/pyspark-storydoc/pyspark-storydoc.git
Project-URL: Bug Reports, https://github.com/pyspark-storydoc/pyspark-storydoc/issues
Project-URL: Changelog, https://github.com/pyspark-storydoc/pyspark-storydoc/blob/main/CHANGELOG.md
Keywords: pyspark,spark,lineage,visualization,business,data-science
Classifier: Development Status :: 3 - Alpha
Classifier: Intended Audience :: Developers
Classifier: Operating System :: OS Independent
Classifier: Programming Language :: Python :: 3
Classifier: Programming Language :: Python :: 3.10
Classifier: Programming Language :: Python :: 3.11
Classifier: Programming Language :: Python :: 3.12
Classifier: Topic :: Software Development :: Libraries :: Python Modules
Classifier: Topic :: Software Development :: Documentation
Classifier: Topic :: Scientific/Engineering :: Information Analysis
Requires-Python: >=3.10
Requires-Dist: pyspark>=3.5.0
Requires-Dist: pandas>=2.0.0
Requires-Dist: numpy>=1.24.0
Requires-Dist: matplotlib>=3.7.0
Requires-Dist: seaborn>=0.12.0
Requires-Dist: pyyaml>=6.0
Requires-Dist: jinja2>=3.1.0
Provides-Extra: dev
Requires-Dist: pytest>=7.4.0; extra == "dev"
Requires-Dist: pytest-cov>=4.1.0; extra == "dev"
Requires-Dist: pytest-mock>=3.11.0; extra == "dev"
Requires-Dist: pytest-timeout>=2.4.0; extra == "dev"
Requires-Dist: black>=23.0.0; extra == "dev"
Requires-Dist: isort>=5.12.0; extra == "dev"
Requires-Dist: flake8>=6.0.0; extra == "dev"
Requires-Dist: mypy>=1.5.0; extra == "dev"
Requires-Dist: pre-commit>=3.3.0; extra == "dev"
Provides-Extra: docs
Requires-Dist: sphinx>=7.1.0; extra == "docs"
Requires-Dist: sphinx-rtd-theme>=1.3.0; extra == "docs"
Requires-Dist: sphinx-autodoc-typehints>=1.24.0; extra == "docs"
Requires-Dist: myst-parser>=2.0.0; extra == "docs"
Provides-Extra: visualization
Requires-Dist: graphviz>=0.20.0; extra == "visualization"
Provides-Extra: all
Requires-Dist: pyspark-storydoc[dev,docs,visualization]; extra == "all"
Dynamic: author
Dynamic: home-page
Dynamic: requires-python
